LICENSE
MANIFEST.in
README.md
setup.py
django_finial.egg-info/PKG-INFO
django_finial.egg-info/SOURCES.txt
django_finial.egg-info/dependency_links.txt
django_finial.egg-info/requires.txt
django_finial.egg-info/top_level.txt
finial/__init__.py
finial/admin.py
finial/context_processors.py
finial/decorators.py
finial/example_settings.py
finial/finders.py
finial/middleware.py
finial/models.py
finial/shortcuts.py
finial/signals.py
finial/util.py
finial/management/__init__.py
finial/management/commands/__init__.py
finial/management/commands/add_or_remove_finial_flag.py
finial/migrations/0001_initial.py
finial/migrations/__init__.py
finial/templatetags/__init__.py
finial/templatetags/finial_flags.py
finial/tests/__init__.py
finial/tests/finial_context_test_overrides.py
finial/tests/finial_test_overrides.py
finial/tests/test_middleware.py
finial/tests/test_signals.py
finial/tests/test_template_context_processor.py
finial/tests/test_templatetag.py
finial/tests/utils.py