Metadata-Version: 1.1
Name: django-finial
Version: 0.7.2
Summary: Template, Static, and URL Overrides per User.
Home-page: http://github.com/urbanairship/django-finial
Author: Gavin McQuillan
Author-email: gavin@urbanairship.com
License: BSD
Platform: UNKNOWN
Classifier: Development Status :: 4 - Beta
Classifier: Environment :: Web Environment
Classifier: Framework :: Django
Classifier: Intended Audience :: Developers
Classifier: License :: OSI Approved :: BSD License
Classifier: Operating System :: OS Independent
Classifier: Programming Language :: Python
Classifier: Topic :: Software Development :: Libraries :: Python Modules
